hepstats/__init__.py
hepstats/_version.py
hepstats/hypotests/README.md
hepstats/hypotests/__init__.py
hepstats/hypotests/exceptions.py
hepstats/hypotests/hypotests_object.py
hepstats/hypotests/parameters.py
hepstats/hypotests/toyutils.py
hepstats/hypotests/calculators/__init__.py
hepstats/hypotests/calculators/asymptotic_calculator.py
hepstats/hypotests/calculators/basecalculator.py
hepstats/hypotests/calculators/frequentist_calculator.py
hepstats/hypotests/core/__init__.py
hepstats/hypotests/core/basetest.py
hepstats/hypotests/core/confidence_interval.py
hepstats/hypotests/core/discovery.py
hepstats/hypotests/core/upperlimit.py
hepstats/modeling/__init__.py
hepstats/modeling/bayesian_blocks.py
hepstats/splot/__init__.py
hepstats/splot/exceptions.py
hepstats/splot/sweights.py
hepstats/splot/warnings.py
hepstats/utils/__init__.py
hepstats/utils/fit/__init__.py
hepstats/utils/fit/api_check.py
hepstats/utils/fit/diverse.py
hepstats/utils/fit/sampling.py
hepstats-0.9.2.dist-info/METADATA
hepstats-0.9.2.dist-info/WHEEL
hepstats-0.9.2.dist-info/RECORD
