Metadata-Version: 2.4
Name: hepstats
Version: 0.9.2
Summary: statistics tools and utilities
Project-URL: Homepage, https://github.com/scikit-hep/hepstats
Author-email: Matthieu Marinangeli <matthieu.marinangeli@gmail.com>
Maintainer-email: Scikit-HEP <scikit-hep-admins@googlegroups.com>
License: BSD 3-Clause License
Classifier: Development Status :: 4 - Beta
Classifier: Intended Audience :: Developers
Classifier: Intended Audience :: Information Technology
Classifier: Intended Audience :: Science/Research
Classifier: License :: OSI Approved :: BSD License
Classifier: Operating System :: MacOS
Classifier: Operating System :: Microsoft :: Windows
Classifier: Operating System :: POSIX
Classifier: Operating System :: Unix
Classifier: Programming Language :: C++
Classifier: Programming Language :: Python
Classifier: Programming Language :: Python :: 3
Classifier: Programming Language :: Python :: 3 :: Only
Classifier: Programming Language :: Python :: 3.9
Classifier: Programming Language :: Python :: 3.10
Classifier: Programming Language :: Python :: 3.11
Classifier: Programming Language :: Python :: 3.12
Classifier: Programming Language :: Python :: 3.13
Classifier: Topic :: Scientific/Engineering
Classifier: Topic :: Scientific/Engineering :: Information Analysis
Classifier: Topic :: Scientific/Engineering :: Mathematics
Classifier: Topic :: Scientific/Engineering :: Physics
Classifier: Topic :: Software Development
Classifier: Topic :: Utilities
Requires-Python: >=3.9
Requires-Dist: asdf
Requires-Dist: numpy
Requires-Dist: pandas
Requires-Dist: scipy
Requires-Dist: tqdm
Requires-Dist: uhi
Provides-Extra: dev
Requires-Dist: matplotlib; extra == 'dev'
Requires-Dist: pre-commit; extra == 'dev'
Requires-Dist: pydata-sphinx-theme; extra == 'dev'
Requires-Dist: pytest; extra == 'dev'
Requires-Dist: pytest-cov; extra == 'dev'
Requires-Dist: pytest-runner; extra == 'dev'
Requires-Dist: sphinx-autodoc-typehints; extra == 'dev'
Requires-Dist: sphinx-copybutton; extra == 'dev'
Requires-Dist: sphinx>=3.1.2; extra == 'dev'
Requires-Dist: sphinxcontrib-bibtex>=2.0.0; extra == 'dev'
Requires-Dist: zfit>=0.20.0; (python_version < '3.13') and extra == 'dev'
Provides-Extra: doc
Requires-Dist: matplotlib; extra == 'doc'
Requires-Dist: pydata-sphinx-theme; extra == 'doc'
Requires-Dist: sphinx-autodoc-typehints; extra == 'doc'
Requires-Dist: sphinx-copybutton; extra == 'doc'
Requires-Dist: sphinx>=3.1.2; extra == 'doc'
Requires-Dist: sphinxcontrib-bibtex>=2.0.0; extra == 'doc'
Provides-Extra: docs
Requires-Dist: matplotlib; extra == 'docs'
Requires-Dist: pydata-sphinx-theme; extra == 'docs'
Requires-Dist: sphinx-autodoc-typehints; extra == 'docs'
Requires-Dist: sphinx-copybutton; extra == 'docs'
Requires-Dist: sphinx>=3.1.2; extra == 'docs'
Requires-Dist: sphinxcontrib-bibtex>=2.0.0; extra == 'docs'
Provides-Extra: test
Requires-Dist: pytest; extra == 'test'
Requires-Dist: pytest-cov; extra == 'test'
Requires-Dist: pytest-runner; extra == 'test'
Requires-Dist: zfit>=0.20.0; (python_version < '3.13') and extra == 'test'
Provides-Extra: zfit
Requires-Dist: zfit>=0.20.0; extra == 'zfit'
